azureml/__init__.py
azureml/acft/__init__.py
azureml/acft/image/__init__.py
azureml/acft/image/components/NOTICE.txt
azureml/acft/image/components/__init__.py
azureml/acft/image/components/_version.py
azureml/acft/image/components/common/__init__.py
azureml/acft/image/components/common/constants.py
azureml/acft/image/components/common/utils.py
azureml/acft/image/components/finetune/__init__.py
azureml/acft/image/components/finetune/finetune_runner.py
azureml/acft/image/components/finetune/common/__init__.py
azureml/acft/image/components/finetune/common/augmentation/__init__.py
azureml/acft/image/components/finetune/common/augmentation/albumentations_augmentation.py
azureml/acft/image/components/finetune/common/augmentation/augmentation_config_utils.py
azureml/acft/image/components/finetune/common/augmentation/base_augmentation.py
azureml/acft/image/components/finetune/common/augmentation/model_preproc_extractor.py
azureml/acft/image/components/finetune/common/augmentation/openmmlab_augmentation.py
azureml/acft/image/components/finetune/common/augmentation/configs/__init__.py
azureml/acft/image/components/finetune/common/augmentation/configs/albumentations_classification.yaml
azureml/acft/image/components/finetune/common/augmentation/configs/albumentations_od_is.yaml
azureml/acft/image/components/finetune/common/constants/__init__.py
azureml/acft/image/components/finetune/common/constants/augmentation_constants.py
azureml/acft/image/components/finetune/common/constants/constants.py
azureml/acft/image/components/finetune/common/data/__init__.py
azureml/acft/image/components/finetune/common/data/base_dataset.py
azureml/acft/image/components/finetune/common/data/classification_dataset.py
azureml/acft/image/components/finetune/common/data/classification_hf_dataset.py
azureml/acft/image/components/finetune/common/data/data_utils.py
azureml/acft/image/components/finetune/common/data/download_manager.py
azureml_acft_image_components-47.0.0.dist-info/LICENSE.txt
azureml_acft_image_components-47.0.0.dist-info/METADATA
azureml_acft_image_components-47.0.0.dist-info/WHEEL
azureml_acft_image_components-47.0.0.dist-info/top_level.txt
azureml_acft_image_components-47.0.0.dist-info/RECORD
