Metadata-Version: 2.1
Name: azureml-acft-image-components
Version: 47.0.0
Summary: Contains the code for vision model's components.
Home-page: https://msdata.visualstudio.com/Vienna/_git/sdk-cli-v2?version=GBtraining_finetune
Author: Microsoft Corp
License: inline_license
Classifier: Development Status :: 2 - Pre-Alpha
Classifier: Intended Audience :: Developers
Classifier: Intended Audience :: Science/Research
Classifier: License :: Other/Proprietary License
Classifier: Programming Language :: Python :: 3.8
Classifier: Programming Language :: Python :: 3.9
Classifier: Programming Language :: Python :: 3.10
Classifier: Topic :: Scientific/Engineering :: Artificial Intelligence
Classifier: Operating System :: Microsoft :: Windows
Classifier: Operating System :: MacOS
Classifier: Operating System :: POSIX :: Linux
Requires-Python: >=3.8,<3.11
License-File: LICENSE.txt
Requires-Dist: albumentations ==1.3.0
Requires-Dist: azureml-mlflow
Requires-Dist: peft ==0.4.0
Provides-Extra: all
Requires-Dist: transformers ==4.33.0 ; extra == 'all'
Provides-Extra: hf
Requires-Dist: transformers ==4.33.0 ; extra == 'hf'
Provides-Extra: mmd
